ess/beer/__init__.py
ess/beer/clustering.py
ess/beer/conversions.py
ess/beer/data.py
ess/beer/io.py
ess/beer/peakfinding.py
ess/beer/types.py
ess/beer/workflow.py
ess/diffraction/__init__.py
ess/diffraction/peaks.py
ess/diffraction/py.typed
ess/dream/__init__.py
ess/dream/beamline.py
ess/dream/data.py
ess/dream/diagnostics.py
ess/dream/instrument_view.py
ess/dream/parameters.py
ess/dream/py.typed
ess/dream/workflows.py
ess/dream/io/__init__.py
ess/dream/io/cif.py
ess/dream/io/geant4.py
ess/powder/__init__.py
ess/powder/_util.py
ess/powder/calibration.py
ess/powder/conversion.py
ess/powder/correction.py
ess/powder/filtering.py
ess/powder/grouping.py
ess/powder/logging.py
ess/powder/masking.py
ess/powder/py.typed
ess/powder/smoothing.py
ess/powder/transform.py
ess/powder/types.py
ess/powder/workflow.py
ess/snspowder/powgen/__init__.py
ess/snspowder/powgen/beamline.py
ess/snspowder/powgen/calibration.py
ess/snspowder/powgen/data.py
ess/snspowder/powgen/instrument_view.py
ess/snspowder/powgen/peaks.py
ess/snspowder/powgen/workflow.py
essdiffraction-26.1.0.dist-info/licenses/LICENSE
essdiffraction-26.1.0.dist-info/METADATA
essdiffraction-26.1.0.dist-info/WHEEL
essdiffraction-26.1.0.dist-info/top_level.txt
essdiffraction-26.1.0.dist-info/RECORD
