Metadata-Version: 2.4
Name: essdiffraction
Version: 26.1.0
Summary: Diffraction data reduction for the European Spallation Source
Author: Scipp contributors
License-Expression: BSD-3-Clause
Project-URL: Bug Tracker, https://github.com/scipp/essdiffraction/issues
Project-URL: Documentation, https://scipp.github.io/essdiffraction
Project-URL: Source, https://github.com/scipp/essdiffraction
Classifier: Intended Audience :: Science/Research
Classifier: Natural Language :: English
Classifier: Operating System :: OS Independent
Classifier: Programming Language :: Python :: 3
Classifier: Programming Language :: Python :: 3 :: Only
Classifier: Programming Language :: Python :: 3.11
Classifier: Programming Language :: Python :: 3.12
Classifier: Programming Language :: Python :: 3.13
Classifier: Topic :: Scientific/Engineering
Classifier: Typing :: Typed
Requires-Python: >=3.11
License-File: LICENSE
Requires-Dist: dask>=2022.1.0
Requires-Dist: essreduce>=25.12.1
Requires-Dist: graphviz
Requires-Dist: numpy>=2
Requires-Dist: plopp>=25.07.0
Requires-Dist: pythreejs>=2.4.1
Requires-Dist: sciline>=25.04.1
Requires-Dist: scipp>=25.11.0
Requires-Dist: scippneutron>=25.02.0
Requires-Dist: scippnexus>=23.12.0
Requires-Dist: tof>=25.11.1
Requires-Dist: ncrystal[cif]>=4.1.0
Requires-Dist: spglib!=2.7
Provides-Extra: test
Requires-Dist: pandas>=2.1.2; extra == "test"
Requires-Dist: pooch>=1.5; extra == "test"
Requires-Dist: pytest>=7.0; extra == "test"
Requires-Dist: ipywidgets>=8.1.7; extra == "test"
Dynamic: license-file
